README.md
setup.py
firefox_tabs/__init__.py
firefox_tabs/fftabs.py
firefox_tabs.egg-info/PKG-INFO
firefox_tabs.egg-info/SOURCES.txt
firefox_tabs.egg-info/dependency_links.txt
firefox_tabs.egg-info/entry_points.txt
firefox_tabs.egg-info/not-zip-safe
firefox_tabs.egg-info/requires.txt
firefox_tabs.egg-info/top_level.txt